{"July 7, 2017":{"Dropped":["Amazon A9 Advertising Technology"]},"June 2, 2017":{"Dropped":["CAPTCHA"]},"May 15, 2017":{"Dropped":["CSS: device width"]},"April 27, 2017":{"Added":["Zinrelo (formerly ShopSocially)"]},"February 3, 2017":{"Added":["CAPTCHA"],"Dropped":["React"]},"November 16, 2016":{"Dropped":["Mixpanel","Zinrelo (formerly ShopSocially)"]},"October 28, 2016":{"Added":["CDNetworks"]},"September 29, 2016":{"Added":["web search bar"]},"August 10, 2016":{"Added":["CSS: device width"]},"January 26, 2016":{"Added":["Zinrelo (formerly ShopSocially)"]},"March 2, 2015":{"Added":["Viewport Meta"]},"January 28, 2015":{"Dropped":["Viewport Meta"]},"December 9, 2014":{"Added":["Google DoubleClick"]},"September 30, 2014":{"Added":["Viewport Meta"]},"May 1, 2014":{"Added":["Dyn Managed DNS (acquired by Oracle)"]},"January 17, 2014":{"Added":["Adobe Analytics (formerly Omniture)"]},"December 6, 2013":{"Dropped":["Adobe Analytics (formerly Omniture)"]},"August 20, 2013":{"Added":["Adobe Analytics (formerly Omniture)"]},"May 16, 2012":{"Dropped":["Neustar UltraDNS"]}}