{"May 22, 2017":{"Added":["Sovrn","Lotame"]},"May 17, 2017":{"Added":["Facebook Atlas","eXelate (acquired by Nielsen)","Altas Relaunched"]},"May 5, 2017":{"Dropped":["Ghostery (formerly Evidon)"]},"April 29, 2017":{"Dropped":["DoubleVerify"]},"April 5, 2017":{"Added":["Google Publisher Tag"]},"March 29, 2017":{"Added":["DoubleVerify"]},"March 18, 2017":{"Added":["Integral Ad Science"]},"March 17, 2017":{"Added":["MediaMath"]},"February 12, 2017":{"Dropped":["Google Font API"]},"January 27, 2017":{"Dropped":["IgnitionOne"]},"January 2, 2017":{"Dropped":["MaxCDN"]},"December 31, 2016":{"Dropped":["Amazon Route 53"]},"December 23, 2016":{"Added":["CloudFlare DNS"],"Dropped":["CSS: font-size em"]},"October 3, 2016":{"Dropped":["MonetizeMore Ad Unit 728 x 90"]},"April 14, 2016":{"Added":["SendGrid","Zendesk","Gmail SPF"]},"March 18, 2016":{"Dropped":["Stripe"]},"January 9, 2016":{"Dropped":["Zendesk","Zendesk Web Widget"]},"October 22, 2015":{"Added":["CSS: font-size em"]},"October 9, 2015":{"Added":["Zendesk","Zendesk Web Widget"]},"July 4, 2015":{"Added":["PayPal"]},"February 27, 2015":{"Dropped":["CloudFlare CDN"]},"February 6, 2015":{"Dropped":["Amazon Web Hosting"]},"January 15, 2015":{"Added":["MaxCDN"]},"December 18, 2014":{"Dropped":["New Relic"]},"October 22, 2014":{"Added":["Google Universal Analytics","Google Font API"]},"August 31, 2014":{"Added":["New Relic"]},"April 1, 2014":{"Dropped":["CloudFlare Hosting"],"Added":["CloudFlare CDN"]},"March 31, 2014":{"Dropped":["CloudFlare Website Optimization","CloudFlare DNS"]},"March 29, 2014":{"Dropped":["GlobalSign"]},"March 25, 2014":{"Added":["Amazon Route 53","GeoTrust","Amazon Web Hosting"]},"March 21, 2014":{"Added":["YouTube"]},"March 19, 2014":{"Added":["Mixpanel"]},"October 29, 2013":{"Added":["nginx"]},"June 28, 2013":{"Added":["Stripe"]},"April 4, 2013":{"Dropped":["Chartbeat"]},"December 27, 2012":{"Added":["CloudFlare Hosting","GlobalSign","CloudFlare Website Optimization"]},"October 24, 2012":{"Dropped":["CloudFlare Website Optimization"]},"February 21, 2012":{"Added":["Google Analytics","Chartbeat"]}}