{"July 13, 2017":{"Added":["Adobe Audience Manager (formerly DemDex)"]},"July 10, 2017":{"Dropped":["Ruby On Rails"]},"July 2, 2017":{"Dropped":["AirPR"]},"June 27, 2017":{"Added":["StickyADS.tv (acquired by FreeWheel)"]},"May 24, 2017":{"Dropped":["Index Exchange (Formerly Casale)"]},"May 21, 2017":{"Dropped":["Google Attribution 360 (formerly Adometry)"]},"May 19, 2017":{"Dropped":["Google Remarketing","Google Dynamic Remarketing"]},"May 18, 2017":{"Added":["WordPress","WordPress 4.7","RawGit","Google Maps"]},"May 15, 2017":{"Added":["Bing Ads"]},"May 8, 2017":{"Added":["Piwik","Express","TVSquared"]},"May 6, 2017":{"Added":["Facebook Atlas"]},"May 4, 2017":{"Added":["PubMatic"]},"April 22, 2017":{"Added":["Yahoo Analytics"]},"March 28, 2017":{"Added":["The Trade Desk"]},"March 20, 2017":{"Added":["Linkedin JavaScript SDK"]},"February 22, 2017":{"Added":["Rocket Fuel"]},"February 20, 2017":{"Added":["New Relic"]},"January 21, 2017":{"Dropped":["ValueClick Mediaplex"]},"December 19, 2016":{"Dropped":["WordPress"]},"December 4, 2016":{"Dropped":["Google Maps","Linkedin JavaScript SDK"]},"November 10, 2016":{"Dropped":["Google Website Optimizer"]},"October 31, 2016":{"Dropped":["LiveRail (acquired by Facebook)"]},"September 30, 2016":{"Dropped":["InsightExpress Flex","iCompass (InsightExpress)"]},"August 16, 2016":{"Added":["Sizmek (formerly MediaMind)"]},"July 11, 2016":{"Dropped":["Sizmek (formerly MediaMind)","Verizon Wireless","TribalFusion (acquired by Exponential)","TubeMogul (acquired by Adobe)","CenturyLink","PointRoll (acquired by Sizmek)"]},"May 8, 2016":{"Dropped":["Collective","Conversant (formerly ValueClick)","NTT America"]},"March 25, 2016":{"Added":["NTT America"]},"January 22, 2016":{"Added":["CenturyLink"]},"August 19, 2015":{"Added":["MailChimp SPF"]},"August 13, 2015":{"Added":["Akamai"]},"August 11, 2015":{"Added":["Verizon Wireless"]},"July 18, 2015":{"Dropped":["Help Scout","Turn","Nanigans"]},"July 16, 2015":{"Dropped":["Cybertrust","CenturyLink"]},"March 27, 2015":{"Added":["CenturyLink"]},"February 2, 2015":{"Added":["Nielsen NetRatings"]},"January 13, 2015":{"Added":["Microsoft Outlook"]},"December 15, 2014":{"Added":["PointRoll (acquired by Sizmek)"]},"December 5, 2014":{"Added":["Facebook Web Custom Audiences"]},"November 1, 2014":{"Added":["AppNexus","Brightroll (acquired by Yahoo!)","Collective","Facebook Login","DoubleClick Floodlight","Turn","Conversant (formerly ValueClick)","TribalFusion (acquired by Exponential)","TubeMogul (acquired by Adobe)","Google Remarketing","Nanigans","Apple App Store links","Right Media (acquired by Yahoo!)","Google Dynamic Remarketing"]},"September 27, 2014":{"Dropped":["Facebook Atlas"]},"August 30, 2014":{"Added":["Sizmek (formerly MediaMind)"]},"August 26, 2014":{"Dropped":["AboveNet (acquired by Zayo)"]},"July 24, 2014":{"Dropped":["Sizmek (formerly MediaMind)"]},"July 21, 2014":{"Dropped":["Brightroll (acquired by Yahoo!)","Collective"]},"May 29, 2014":{"Dropped":["Nielsen NetRatings"]},"May 21, 2014":{"Added":["Sizmek (formerly MediaMind)"]},"April 9, 2014":{"Added":["BlueKai (acquired by Oracle)"]},"March 28, 2014":{"Added":["Brightroll (acquired by Yahoo!)","Collective"]},"February 4, 2014":{"Added":["AboveNet (acquired by Zayo)"]},"November 8, 2013":{"Dropped":["GTE Corporation"]},"October 28, 2013":{"Added":["Cybertrust"]},"October 20, 2013":{"Dropped":["Sizmek (formerly MediaMind)"]},"September 16, 2013":{"Added":["Sizmek (formerly MediaMind)"]},"June 16, 2013":{"Dropped":["Sizmek (formerly MediaMind)"]},"May 17, 2013":{"Added":["Nielsen NetRatings"]},"May 10, 2013":{"Added":["Help Scout"]},"March 3, 2013":{"Added":["Google Website Optimizer"]},"February 27, 2013":{"Added":["Facebook Atlas"]},"February 22, 2013":{"Dropped":["Nielsen NetRatings"]},"February 7, 2013":{"Added":["Sizmek (formerly MediaMind)"]},"November 27, 2012":{"Dropped":["Facebook Atlas"]},"October 23, 2012":{"Added":["Nielsen NetRatings","Facebook Atlas"]},"October 13, 2012":{"Added":["Google DoubleClick"]},"March 2, 2012":{"Added":["Google Analytics"]}}