{"July 7, 2017":{"Added":["AppNexus Open AdStream"]},"July 3, 2017":{"Dropped":["Amazon A9 Advertising Technology"]},"June 30, 2017":{"Dropped":["SiteScout (acquired by Centro)"]},"June 16, 2017":{"Dropped":["Dstillery (formerly Media6Degrees)"]},"June 2, 2017":{"Dropped":["Drawbridge"]},"June 1, 2017":{"Dropped":["Jivox"]},"May 30, 2017":{"Added":["Doubleclick Bid Manager","DoubleClick for Publishers Video Ads","jsDelivr"],"Dropped":["greyscale - grey","Bit.ly"]},"May 8, 2017":{"Added":["Comodo"],"Dropped":["GeoTrust"]},"April 17, 2017":{"Added":["Drawbridge"]},"April 13, 2017":{"Added":["Google Publisher Tag"]},"April 12, 2017":{"Added":["Chartbeat"]},"April 3, 2017":{"Added":["Clicktale"]},"March 31, 2017":{"Added":["Twitter Ads"]},"March 27, 2017":{"Added":["Jivox"]},"March 21, 2017":{"Added":["Qualtrics Site Intercept","Qualtrics"]},"March 19, 2017":{"Added":["Rocket Fuel","CSS: device width"]},"March 1, 2017":{"Added":["Facebook Atlas"]},"February 25, 2017":{"Added":["Celtra"]},"January 20, 2017":{"Dropped":["Zergnet"]},"January 13, 2017":{"Dropped":["Salesforce Desk.com"]},"January 11, 2017":{"Dropped":["Schema.org"]},"January 6, 2017":{"Dropped":["YouTube"]},"January 3, 2017":{"Added":["Nielsen NetRatings","SpotX"],"Dropped":["web search bar"]},"December 29, 2016":{"Dropped":["Celtra"]},"November 30, 2016":{"Dropped":["Nielsen NetRatings","LiveRail (acquired by Facebook)","The Trade Desk"]},"November 22, 2016":{"Added":["web search bar"]},"November 19, 2016":{"Dropped":["Ooyala"]},"November 9, 2016":{"Added":["Adobe Dynamic Tag Management","Facebook WCA Page View"]},"October 19, 2016":{"Added":["Ooyala"]},"October 12, 2016":{"Dropped":["Videoplaza (acquired by Ooyala)","YuMe","WebSpectator","PointRoll (acquired by Sizmek)","YieldBot","PulsePoint","Index Exchange (Formerly Casale)"]},"September 30, 2016":{"Added":["The Trade Desk"],"Dropped":["Disqus","Ad Unit 320 x 50"]},"July 14, 2016":{"Dropped":["Lotame","GoDaddy SSL","Turn","Conversant (formerly ValueClick)","Glam Media","Specific Media","SpotX","Adform","Undertone","Veruta (acquired by MyBuys)","Twitter Ads"]},"June 17, 2016":{"Added":["Google Maps","Google Maps (Non Paid Users)"]},"May 12, 2016":{"Dropped":["Facebook Atlas","[x+1] (acquired by Rocket Fuel)","The Trade Desk","Yieldr"]},"April 11, 2016":{"Added":["Schema.org"]},"February 23, 2016":{"Dropped":["Adition Technologies - Publishers","Google Maps","Korrelate","Switch Concepts"]},"January 26, 2016":{"Added":["Mailchimp Mandrill"]},"October 6, 2015":{"Added":["Switch Concepts"]},"July 31, 2015":{"Added":["Yieldr"]},"July 27, 2015":{"Dropped":["JQuery 1.11.1"]},"June 25, 2015":{"Added":["DoubleClick Floodlight"]},"June 23, 2015":{"Added":["Undertone","Google Maps","TRUSTe"],"Dropped":["DataXu"]},"May 5, 2015":{"Added":["Korrelate"]},"April 8, 2015":{"Added":["Conversant (formerly ValueClick)","Yahoo Analytics"]},"March 29, 2015":{"Added":["DataXu","Adition Technologies - Publishers"]},"March 28, 2015":{"Added":["Nielsen NetRatings","Ghostery (formerly Evidon)"],"Dropped":["LinkedIn Display Ads (formerly Bizo)","Brilig (acquired by Merkle)"]},"February 25, 2015":{"Dropped":["DoubleClick Floodlight"]},"February 15, 2015":{"Dropped":["Undertone"]},"February 4, 2015":{"Dropped":["Nielsen NetRatings"]},"January 26, 2015":{"Added":["Lotame","Advertising.com","OwnerIQ"]},"January 16, 2015":{"Dropped":["SoundCloud","Ghostery (formerly Evidon)"]},"January 3, 2015":{"Added":["BlueKai (acquired by Oracle)","Adform","[x+1] (acquired by Rocket Fuel)","Veruta (acquired by MyBuys)","Videology"]},"December 27, 2014":{"Added":["Integral Ad Science"],"Dropped":["Acxiom"]},"December 23, 2014":{"Added":["Specific Media","SpotX","The Trade Desk"]},"December 7, 2014":{"Added":["Twitter Ads"]},"November 20, 2014":{"Added":["Facebook Atlas","DoubleVerify"],"Dropped":["Specific Media"]},"November 17, 2014":{"Added":["Viewport Meta"]},"November 11, 2014":{"Added":["YouTube"]},"November 4, 2014":{"Added":["Google Attribution 360 (formerly Adometry)"]},"November 2, 2014":{"Dropped":["Yahoo Analytics","Lotame"]},"October 26, 2014":{"Added":["JQuery 1.11.1","Amazon Associates"],"Dropped":["CDNetworks"]},"October 2, 2014":{"Added":["LinkedIn Display Ads (formerly Bizo)","Rubicon Project","Brilig (acquired by Merkle)","Acxiom"]},"September 27, 2014":{"Added":["Salesforce Desk.com","reCAPTCHA","eXelate (acquired by Nielsen)","Yahoo Analytics"]},"September 22, 2014":{"Added":["Specific Media"]},"September 16, 2014":{"Added":["Amazon CloudFront"]},"September 11, 2014":{"Added":["Google Apps","Gmail for business"]},"September 6, 2014":{"Dropped":["YouTube"]},"August 16, 2014":{"Added":["Right Media (acquired by Yahoo!)"]},"August 12, 2014":{"Added":["DoubleClick Floodlight","Turn","Zergnet"]},"August 2, 2014":{"Added":["Lotame","Sizmek (formerly MediaMind)","Moat","Undertone"]},"July 16, 2014":{"Added":["ValueClick Mediaplex"]},"June 19, 2014":{"Added":["Ghostery (formerly Evidon)"]},"April 19, 2014":{"Added":["SoundCloud"]},"April 9, 2014":{"Added":["Glam Media"]},"April 3, 2014":{"Added":["Google DoubleClick"]},"April 2, 2014":{"Added":["JW Player"]},"March 2, 2014":{"Dropped":["Mass Relevance (acquired by Spredfast)"]},"February 15, 2014":{"Dropped":["Google DoubleClick"]},"February 14, 2014":{"Added":["YouTube"]},"February 10, 2014":{"Dropped":["Level 3 CDN"]},"January 31, 2014":{"Added":["Krux (acquired by Salesforce)"]},"January 17, 2014":{"Added":["Google Tag Manager"]},"January 4, 2014":{"Added":["Facebook Login"]},"January 2, 2014":{"Added":["Apache HTTP Server"]},"November 14, 2013":{"Dropped":["Facebook Login"]},"October 30, 2013":{"Added":["Level 3 CDN"]},"October 29, 2013":{"Added":["Google DoubleClick"]},"September 14, 2013":{"Dropped":["Google DoubleClick"]},"September 9, 2013":{"Dropped":["Instart Logic"]},"August 17, 2013":{"Added":["Adobe Analytics (formerly Omniture)"]},"August 1, 2013":{"Dropped":["Comodo"]},"July 31, 2013":{"Added":["GoDaddy SSL"]},"July 2, 2013":{"Dropped":["Lotame","Salesforce Desk.com"]},"June 19, 2013":{"Dropped":["YouTube"]},"June 15, 2013":{"Dropped":["Amazon Widgets","Vibrant Media"]},"June 12, 2013":{"Dropped":["AddThis"]},"June 9, 2013":{"Dropped":["Chartbeat"]},"December 3, 2012":{"Added":["Comodo"]},"August 13, 2012":{"Added":["Nielsen NetRatings"]},"May 10, 2012":{"Added":["CDNetworks"]}}