{"July 12, 2017":{"Added":["Sizmek (formerly MediaMind)"]},"May 23, 2017":{"Added":["Cybertrust"]},"May 5, 2017":{"Dropped":["nginx","Sizmek (formerly MediaMind)","Google DoubleClick"]},"April 7, 2017":{"Added":["Apache HTTP Server"]},"March 4, 2017":{"Added":["Sizmek (formerly MediaMind)"]},"March 2, 2017":{"Added":["Google DoubleClick"]},"January 15, 2017":{"Dropped":["Sizmek (formerly MediaMind)"]},"September 16, 2016":{"Dropped":["Signal by BrightTag"]},"June 24, 2016":{"Dropped":["AD EBiS","AppNexus Open AdStream","Google DoubleClick"]},"April 12, 2016":{"Added":["AppNexus"]},"March 14, 2016":{"Added":["Google DoubleClick"]},"February 11, 2016":{"Dropped":["Facebook Atlas","Altas Relaunched"]},"January 7, 2016":{"Added":["AD EBiS"]},"November 3, 2015":{"Added":["Facebook Atlas","Altas Relaunched"]},"October 8, 2015":{"Dropped":["Google DoubleClick"]},"July 21, 2015":{"Dropped":["AD EBiS"]},"July 3, 2015":{"Added":["AppNexus Open AdStream"]},"June 30, 2015":{"Dropped":["Facebook Atlas","Altas Relaunched"],"Added":["Google DoubleClick"]},"March 31, 2015":{"Added":["Altas Relaunched","Facebook Atlas"]},"January 27, 2015":{"Added":["AD EBiS"],"Dropped":["Google DoubleClick"]},"January 18, 2015":{"Dropped":["Facebook Atlas"]},"December 3, 2014":{"Added":["Facebook Atlas"]},"October 29, 2014":{"Dropped":["AD EBiS"]},"September 1, 2014":{"Dropped":["Facebook Atlas"]},"July 21, 2014":{"Added":["Facebook Atlas"]},"July 6, 2014":{"Dropped":["Facebook Widget"]},"April 30, 2014":{"Added":["AD EBiS"]},"January 13, 2014":{"Dropped":["Facebook Atlas"]},"January 12, 2014":{"Added":["Sizmek (formerly MediaMind)"]},"October 27, 2013":{"Added":["Facebook Atlas"]},"October 21, 2013":{"Dropped":["YouTube"]},"August 29, 2013":{"Added":["Facebook Widget"]},"June 15, 2013":{"Dropped":["Facebook Widget"]},"May 10, 2013":{"Added":["YouTube"]},"April 8, 2013":{"Added":["Google DoubleClick"]},"March 6, 2013":{"Dropped":["Sizmek (formerly MediaMind)"]},"February 13, 2013":{"Dropped":["Facebook Atlas"]},"January 27, 2013":{"Added":["Sizmek (formerly MediaMind)"]},"January 4, 2013":{"Added":["Facebook Atlas"]}}