{"object_type":"company","domain":"ci123.com","properties":{"name":"育儿网","domain":"ci123.com","location":{"state":null,"state_code":null,"country":null,"country_code":null,"tags":["unknown_gdp_per_capita"]},"number_of_employees":5,"industry":null,"customer_fit":{"segment":"not enough information","top_signals":[{"name":"employee count","value":5,"type":"negative"},{"name":"web traffic volume","value":"very high","type":"positive"}]},"customer_fit_self_serve":{"segment":"medium","top_signals":[{"name":"employee count","value":5,"type":"negative"},{"name":"web traffic volume","value":"very high","type":"positive"}]}}}